{
  "_generated": "Generated by SweetTooth, do not edit", 
  "description": "Watch youtube while working\n\n\nOpen YouTube in separate window. Move it to other workspace. (Ctrl+Shift+Alt+Down, or by mouse), return to your workspace (Ctrl+Alt+Up)", 
  "extension-id": "youtube-float-window", 
  "name": "YouTube popup web-browser extention", 
  "shell-version": [
    "3.36.3"
  ], 
  "url": "https://github.com/Ulisses1478/float-youtube-for-gnome-3.30", 
  "uuid": "youtube-float-window@ulisses1478", 
  "version": 1
}